{
  "name": "美股盤前情報資料庫",
  "updated_at": "2026-07-22T22:42:41.632123+08:00",
  "next_update_at": "2026-07-22T14:50:00Z",
  "stocks": [
    "MSFT",
    "GOOG",
    "NVDA",
    "NOW",
    "TSM",
    "MRVL",
    "AVGO",
    "MU",
    "SNDK",
    "SPCX"
  ],
  "data": {
    "MSFT": {
      "name": "Microsoft Corporation",
      "quote": {
        "c": 388.5,
        "d": -9.25,
        "dp": -2.3256,
        "regular": 388.5,
        "reg_d": -9.25,
        "reg_dp": -2.3256,
        "pre": null,
        "post": null,
        "prev_close": 397.75,
        "phase": "正式盤"
      },
      "news": [
        {
          "headline": "3M turns to AI to fuel turnaround",
          "datetime": 1784674893,
          "source": "Yahoo Finance",
          "url": "https://finance.yahoo.com/video/3m-turns-to-ai-to-fuel-turnaround-194739770.html"
        }
      ]
    },
    "GOOG": {
      "name": "Alphabet Inc.",
      "quote": {
        "c": 347.63,
        "d": 1.44,
        "dp": 0.416,
        "regular": 347.63,
        "reg_d": 1.44,
        "reg_dp": 0.416,
        "pre": null,
        "post": null,
        "prev_close": 346.19,
        "phase": "正式盤"
      },
      "news": [
        {
          "headline": "Earnings live: Danaher stock plunges on trimmed forecast, 3M stock surges",
          "datetime": 1784674893,
          "source": "Yahoo Finance",
          "url": "https://finance.yahoo.com/markets/live/earnings-live-second-quarter-results-tesla-google-july-115324842.html"
        }
      ]
    },
    "NVDA": {
      "name": "NVIDIA Corporation",
      "quote": {
        "c": 207.53,
        "d": 0.24,
        "dp": 0.1167,
        "regular": 207.53,
        "reg_d": 0.24,
        "reg_dp": 0.1167,
        "pre": null,
        "post": null,
        "prev_close": 207.29,
        "phase": "正式盤"
      },
      "news": [
        {
          "headline": "Big Tech's big AI spending is 'a good thing' right now",
          "datetime": 1784674893,
          "source": "Yahoo Finance",
          "url": "https://finance.yahoo.com/video/big-techs-big-ai-spending-is-a-good-thing-right-now-203258720.html"
        }
      ]
    },
    "NOW": {
      "name": "ServiceNow, Inc.",
      "quote": {
        "c": 97.12,
        "d": -4.94,
        "dp": -4.8403,
        "regular": 97.12,
        "reg_d": -4.94,
        "reg_dp": -4.8403,
        "pre": null,
        "post": null,
        "prev_close": 102.06,
        "phase": "正式盤"
      },
      "news": [
        {
          "headline": "Google & Tesla kick off Big Tech earnings: What to Watch",
          "datetime": 1784674893,
          "source": "Yahoo Finance",
          "url": "https://finance.yahoo.com/video/google--tesla-kick-off-big-tech-earnings-what-to-watch-210020832.html"
        }
      ]
    },
    "TSM": {
      "name": "Taiwan Semiconductor Manufactur",
      "quote": {
        "c": 421.71,
        "d": -2.9,
        "dp": -0.683,
        "regular": 421.71,
        "reg_d": -2.9,
        "reg_dp": -0.683,
        "pre": null,
        "post": null,
        "prev_close": 424.61,
        "phase": "正式盤"
      },
      "news": [
        {
          "headline": "Intel, KLA Corporation, Lam Research, Marvell Technology, and Micron Shares Skyrocket, What You Need To Know",
          "datetime": 1784674893,
          "source": "Yahoo Finance",
          "url": "https://finance.yahoo.com/markets/stocks/articles/intel-kla-corporation-lam-research-205426906.html"
        }
      ]
    },
    "MRVL": {
      "name": "Marvell Technology, Inc.",
      "quote": {
        "c": 209.75,
        "d": 1.79,
        "dp": 0.8607,
        "regular": 209.75,
        "reg_d": 1.79,
        "reg_dp": 0.8607,
        "pre": null,
        "post": null,
        "prev_close": 207.96,
        "phase": "正式盤"
      },
      "news": [
        {
          "headline": "Intel, KLA Corporation, Lam Research, Marvell Technology, and Micron Shares Skyrocket, What You Need To Know",
          "datetime": 1784674893,
          "source": "Yahoo Finance",
          "url": "https://finance.yahoo.com/markets/stocks/articles/intel-kla-corporation-lam-research-205426906.html"
        }
      ]
    },
    "AVGO": {
      "name": "Broadcom Inc.",
      "quote": {
        "c": 387.12,
        "d": 0.62,
        "dp": 0.1617,
        "regular": 387.12,
        "reg_d": 0.62,
        "reg_dp": 0.1617,
        "pre": null,
        "post": null,
        "prev_close": 386.5,
        "phase": "正式盤"
      },
      "news": [
        {
          "headline": "Jim Cramer Says Stop Betting on Volatile Tech Stocks and Buy These “Boring” Sectors Instead",
          "datetime": 1784674893,
          "source": "Yahoo Finance",
          "url": "https://247wallst.com/investing/2026/07/21/jim-cramer-says-stop-betting-on-volatile-tech-stocks-and-buy-these-boring-sectors-instead/"
        }
      ]
    },
    "MU": {
      "name": "Micron Technology, Inc.",
      "quote": {
        "c": 966.49,
        "d": -4.33,
        "dp": -0.446,
        "regular": 966.49,
        "reg_d": -4.33,
        "reg_dp": -0.446,
        "pre": null,
        "post": null,
        "prev_close": 970.82,
        "phase": "正式盤"
      },
      "news": [
        {
          "headline": "Why GM's memory chip guidance could help stabilize stocks like Micron and Sandisk",
          "datetime": 1784674893,
          "source": "Yahoo Finance",
          "url": "https://finance.yahoo.com/markets/stocks/article/why-gms-memory-chip-guidance-could-help-stabilize-stocks-like-micron-and-sandisk-120313927.html"
        }
      ]
    },
    "SNDK": {
      "name": "Sandisk Corporation",
      "quote": {
        "c": 1587.31,
        "d": -2.09,
        "dp": -0.1315,
        "regular": 1587.31,
        "reg_d": -2.09,
        "reg_dp": -0.1315,
        "pre": null,
        "post": null,
        "prev_close": 1589.4,
        "phase": "正式盤"
      },
      "news": [
        {
          "headline": "Why GM's memory chip guidance could help stabilize stocks like Micron and Sandisk",
          "datetime": 1784674893,
          "source": "Yahoo Finance",
          "url": "https://finance.yahoo.com/markets/stocks/article/why-gms-memory-chip-guidance-could-help-stabilize-stocks-like-micron-and-sandisk-120313927.html"
        }
      ]
    },
    "SPCX": {
      "name": "Space Exploration Technologies",
      "quote": {
        "c": 122.77,
        "d": -0.78,
        "dp": -0.6273,
        "regular": 122.77,
        "reg_d": -0.78,
        "reg_dp": -0.6273,
        "pre": null,
        "post": null,
        "prev_close": 123.54,
        "phase": "正式盤"
      },
      "news": [
        {
          "headline": "Jamie Dimon throws caution on the AI frenzy but sees promise in space data centers",
          "datetime": 1784674893,
          "source": "Yahoo Finance",
          "url": "https://finance.yahoo.com/markets/article/jamie-dimon-throws-caution-on-the-ai-frenzy-but-sees-promise-in-space-data-centers-182215908.html"
        }
      ]
    }
  },
  "alert_sent": {
    "morning": "2026-07-22",
    "evening": "2026-07-22"
  }
}