{
  "name": "美股盤前情報資料庫",
  "updated_at": "2026-06-02T17:30:16.799379+00:00",
  "data": {
    "NOW": {
      "quote": {
        "c": 126.66999816894531,
        "d": -5.320001831054697,
        "dp": -4.030609766690428
      },
      "news": [
        {
          "headline": "無新聞標題",
          "datetime": 1780421415,
          "source": "Yahoo Finance",
          "url": "#"
        },
        {
          "headline": "無新聞標題",
          "datetime": 1780421415,
          "source": "Yahoo Finance",
          "url": "#"
        },
        {
          "headline": "無新聞標題",
          "datetime": 1780421415,
          "source": "Yahoo Finance",
          "url": "#"
        }
      ]
    },
    "NVDA": {
      "quote": {
        "c": 224.16050720214844,
        "d": 0.24050720214845,
        "dp": 0.10740764654718203
      },
      "news": [
        {
          "headline": "無新聞標題",
          "datetime": 1780421415,
          "source": "Yahoo Finance",
          "url": "#"
        },
        {
          "headline": "無新聞標題",
          "datetime": 1780421415,
          "source": "Yahoo Finance",
          "url": "#"
        },
        {
          "headline": "無新聞標題",
          "datetime": 1780421415,
          "source": "Yahoo Finance",
          "url": "#"
        }
      ]
    },
    "LITE": {
      "quote": {
        "c": 1032.760009765625,
        "d": 118.46000976562505,
        "dp": 12.956361124972663
      },
      "news": [
        {
          "headline": "無新聞標題",
          "datetime": 1780421415,
          "source": "Yahoo Finance",
          "url": "#"
        },
        {
          "headline": "無新聞標題",
          "datetime": 1780421415,
          "source": "Yahoo Finance",
          "url": "#"
        },
        {
          "headline": "無新聞標題",
          "datetime": 1780421415,
          "source": "Yahoo Finance",
          "url": "#"
        }
      ]
    },
    "ONDS": {
      "quote": {
        "c": 13.625,
        "d": 0.2142999999999997,
        "dp": 1.597977734197318
      },
      "news": [
        {
          "headline": "無新聞標題",
          "datetime": 1780421416,
          "source": "Yahoo Finance",
          "url": "#"
        },
        {
          "headline": "無新聞標題",
          "datetime": 1780421416,
          "source": "Yahoo Finance",
          "url": "#"
        },
        {
          "headline": "無新聞標題",
          "datetime": 1780421416,
          "source": "Yahoo Finance",
          "url": "#"
        }
      ]
    },
    "MRVL": {
      "quote": {
        "c": 284.8349914550781,
        "d": 65.34199145507813,
        "dp": 29.769510396722502
      },
      "news": [
        {
          "headline": "無新聞標題",
          "datetime": 1780421416,
          "source": "Yahoo Finance",
          "url": "#"
        },
        {
          "headline": "無新聞標題",
          "datetime": 1780421416,
          "source": "Yahoo Finance",
          "url": "#"
        },
        {
          "headline": "無新聞標題",
          "datetime": 1780421416,
          "source": "Yahoo Finance",
          "url": "#"
        }
      ]
    },
    "GOOG": {
      "quote": {
        "c": 364.0899963378906,
        "d": -5.910003662109375,
        "dp": -1.597298287056588
      },
      "news": [
        {
          "headline": "無新聞標題",
          "datetime": 1780421416,
          "source": "Yahoo Finance",
          "url": "#"
        },
        {
          "headline": "無新聞標題",
          "datetime": 1780421416,
          "source": "Yahoo Finance",
          "url": "#"
        },
        {
          "headline": "無新聞標題",
          "datetime": 1780421416,
          "source": "Yahoo Finance",
          "url": "#"
        }
      ]
    }
  }
}