{
  "name": "美股盤前情報資料庫",
  "updated_at": "2026-07-11T03:22:28.442415+08:00",
  "next_update_at": "2026-07-10T19:30:00Z",
  "stocks": [
    "NOW",
    "NVDA",
    "LITE",
    "ONDS",
    "MRVL",
    "GOOG",
    "SPCX",
    "TSM",
    "MU",
    "SNDK",
    "TSLA",
    "MSFT"
  ],
  "data": {
    "NOW": {
      "name": "ServiceNow, Inc.",
      "quote": {
        "c": 107.85,
        "d": -0.99,
        "dp": -0.9096,
        "regular": 107.85,
        "reg_d": -0.99,
        "reg_dp": -0.9096,
        "pre": null,
        "post": null,
        "prev_close": 108.84,
        "phase": "正式盤"
      },
      "news": [
        {
          "headline": "Chip Stocks Drop 12% as Software Rebounds in AI Trade Shift",
          "datetime": 1783640047,
          "source": "Yahoo Finance",
          "url": "https://finance.yahoo.com/technology/ai/articles/chip-stocks-drop-12-software-183927139.html"
        }
      ]
    },
    "NVDA": {
      "name": "NVIDIA Corporation",
      "quote": {
        "c": 209.82,
        "d": 7.04,
        "dp": 3.4717,
        "regular": 209.82,
        "reg_d": 7.04,
        "reg_dp": 3.4717,
        "pre": null,
        "post": null,
        "prev_close": 202.78,
        "phase": "正式盤"
      },
      "news": [
        {
          "headline": "SK Hynix's US listing, Delta earnings, housing bill: What to Watch",
          "datetime": 1783640047,
          "source": "Yahoo Finance",
          "url": "https://finance.yahoo.com/video/sk-hynixs-us-listing-delta-230000258.html"
        }
      ]
    },
    "LITE": {
      "name": "Lumentum Holdings Inc.",
      "quote": {
        "c": 796.18,
        "d": 10.41,
        "dp": 1.3248,
        "regular": 796.18,
        "reg_d": 10.41,
        "reg_dp": 1.3248,
        "pre": null,
        "post": null,
        "prev_close": 785.77,
        "phase": "正式盤"
      },
      "news": [
        {
          "headline": "Lumentum, Sandisk, Applied Materials, AstraZeneca, and More Stocks That Explain Todayâs Market",
          "datetime": 1783640047,
          "source": "Yahoo Finance",
          "url": "https://www.barrons.com/articles/stock-movers-35ab3cc0?siteid=yhoof2&yptr=yahoo"
        }
      ]
    },
    "ONDS": {
      "name": "Ondas Inc",
      "quote": {
        "c": 7.25,
        "d": -0.41,
        "dp": -5.2941,
        "regular": 7.25,
        "reg_d": -0.41,
        "reg_dp": -5.2941,
        "pre": null,
        "post": null,
        "prev_close": 7.65,
        "phase": "正式盤"
      },
      "news": [
        {
          "headline": "Ondas (ONDS) Could Be 62% Undervalued Following Its $875.8 Million DZYNE Deal",
          "datetime": 1783640047,
          "source": "Yahoo Finance",
          "url": "https://finance.yahoo.com/markets/stocks/articles/ondas-onds-could-62-undervalued-191208751.html"
        }
      ]
    },
    "MRVL": {
      "name": "Marvell Technology, Inc.",
      "quote": {
        "c": 236.32,
        "d": -6.95,
        "dp": -2.8569,
        "regular": 236.32,
        "reg_d": -6.95,
        "reg_dp": -2.8569,
        "pre": null,
        "post": null,
        "prev_close": 243.27,
        "phase": "正式盤"
      },
      "news": [
        {
          "headline": "Micron, Sandisk, Marvell stocks jump, leading chip sector gains",
          "datetime": 1783640047,
          "source": "Yahoo Finance",
          "url": "https://finance.yahoo.com/markets/stocks/article/micron-sandisk-marvell-stocks-jump-leading-chip-sector-gains-135433074.html"
        }
      ]
    },
    "GOOG": {
      "name": "Alphabet Inc.",
      "quote": {
        "c": 354.16,
        "d": -2.08,
        "dp": -0.5839,
        "regular": 354.16,
        "reg_d": -2.08,
        "reg_dp": -0.5839,
        "pre": null,
        "post": null,
        "prev_close": 356.24,
        "phase": "正式盤"
      },
      "news": [
        {
          "headline": "SK Hynix's US listing, Delta earnings, housing bill: What to Watch",
          "datetime": 1783640047,
          "source": "Yahoo Finance",
          "url": "https://finance.yahoo.com/video/sk-hynixs-us-listing-delta-230000258.html"
        }
      ]
    },
    "SPCX": {
      "name": "Space Exploration Technologies",
      "quote": {
        "c": 148.16,
        "d": -4.0,
        "dp": -2.6312,
        "regular": 148.16,
        "reg_d": -4.0,
        "reg_dp": -2.6312,
        "pre": null,
        "post": null,
        "prev_close": 152.16,
        "phase": "正式盤"
      },
      "news": [
        {
          "headline": "SK Hynix is the talk of the town. Is IPO day the right time to buy?",
          "datetime": 1783640047,
          "source": "Yahoo Finance",
          "url": "https://finance.yahoo.com/video/sk-hynix-talk-town-ipo-155738106.html"
        }
      ]
    },
    "TSM": {
      "name": "Taiwan Semiconductor Manufactur",
      "quote": {
        "c": 436.35,
        "d": -0.61,
        "dp": -0.1396,
        "regular": 436.35,
        "reg_d": -0.61,
        "reg_dp": -0.1396,
        "pre": null,
        "post": null,
        "prev_close": 436.96,
        "phase": "正式盤"
      },
      "news": [
        {
          "headline": "SK Hynix's US listing, Delta earnings, housing bill: What to Watch",
          "datetime": 1783640047,
          "source": "Yahoo Finance",
          "url": "https://finance.yahoo.com/video/sk-hynixs-us-listing-delta-230000258.html"
        }
      ]
    },
    "MU": {
      "name": "Micron Technology, Inc.",
      "quote": {
        "c": 991.01,
        "d": -0.62,
        "dp": -0.063,
        "regular": 991.01,
        "reg_d": -0.62,
        "reg_dp": -0.063,
        "pre": null,
        "post": null,
        "prev_close": 991.64,
        "phase": "正式盤"
      },
      "news": [
        {
          "headline": "Micron, Sandisk, Marvell stocks jump, leading chip sector gains",
          "datetime": 1783640047,
          "source": "Yahoo Finance",
          "url": "https://finance.yahoo.com/markets/stocks/article/micron-sandisk-marvell-stocks-jump-leading-chip-sector-gains-135433074.html"
        }
      ]
    },
    "SNDK": {
      "name": "Sandisk Corporation",
      "quote": {
        "c": 1921.51,
        "d": 63.24,
        "dp": 3.4032,
        "regular": 1921.51,
        "reg_d": 63.24,
        "reg_dp": 3.4032,
        "pre": null,
        "post": null,
        "prev_close": 1858.27,
        "phase": "正式盤"
      },
      "news": [
        {
          "headline": "Micron, Sandisk, Marvell stocks jump, leading chip sector gains",
          "datetime": 1783640047,
          "source": "Yahoo Finance",
          "url": "https://finance.yahoo.com/markets/stocks/article/micron-sandisk-marvell-stocks-jump-leading-chip-sector-gains-135433074.html"
        }
      ]
    },
    "TSLA": {
      "name": "Tesla, Inc.",
      "quote": {
        "c": 409.67,
        "d": 3.12,
        "dp": 0.7674,
        "regular": 409.67,
        "reg_d": 3.12,
        "reg_dp": 0.7674,
        "pre": null,
        "post": null,
        "prev_close": 406.55,
        "phase": "正式盤"
      },
      "news": [
        {
          "headline": "Did Teslaâs Miami Robotaxi Launch and Q2 Numbers Just Shift TSLAâs AutonomyâFirst Narrative?",
          "datetime": 1783640047,
          "source": "Yahoo Finance",
          "url": "https://finance.yahoo.com/markets/stocks/articles/did-tesla-miami-robotaxi-launch-221357688.html"
        }
      ]
    },
    "MSFT": {
      "name": "Microsoft Corporation",
      "quote": {
        "c": 385.35,
        "d": 0.99,
        "dp": 0.2565,
        "regular": 385.35,
        "reg_d": 0.99,
        "reg_dp": 0.2565,
        "pre": null,
        "post": null,
        "prev_close": 384.36,
        "phase": "正式盤"
      },
      "news": [
        {
          "headline": "暫無最新新聞",
          "datetime": 1783688425,
          "source": "Yahoo Finance",
          "url": "#"
        }
      ]
    }
  },
  "alert_sent": {
    "morning": "2026-07-09",
    "evening": "2026-07-10"
  }
}