{
  "name": "美股盤前情報資料庫",
  "updated_at": "2026-07-01T20:19:13.217377+08:00",
  "data": {
    "NOW": {
      "quote": {
        "c": 103.88,
        "d": 3.91,
        "dp": 3.9122,
        "regular": 99.28,
        "reg_d": -0.69,
        "reg_dp": -0.6902,
        "pre": 103.88,
        "post": null,
        "prev_close": 99.97,
        "phase": "盤前"
      },
      "news": [
        {
          "headline": "Is The Market Ignoring The Real Growth Story In Salesforce Stock?",
          "datetime": 1782859817,
          "source": "Yahoo Finance",
          "url": "https://www.trefis.com/articles/605160/is-the-market-ignoring-the-real-growth-story-in-salesforce-stock/2026-06-30"
        }
      ]
    },
    "NVDA": {
      "quote": {
        "c": 198.95,
        "d": 3.98,
        "dp": 2.0426,
        "regular": 200.09,
        "reg_d": 5.12,
        "reg_dp": 2.626,
        "pre": 198.95,
        "post": null,
        "prev_close": 194.97,
        "phase": "盤前"
      },
      "news": [
        {
          "headline": "Nvidia stock is sagging. Here's what's behind the negative short-term trend.",
          "datetime": 1782859817,
          "source": "Yahoo Finance",
          "url": "https://finance.yahoo.com/markets/stocks/article/nvidia-stock-is-sagging-heres-whats-behind-the-negative-short-term-trend-120447121.html"
        }
      ]
    },
    "LITE": {
      "quote": {
        "c": 843.9,
        "d": -7.5,
        "dp": -0.8809,
        "regular": 858.06,
        "reg_d": 6.66,
        "reg_dp": 0.7822,
        "pre": 843.9,
        "post": null,
        "prev_close": 851.4,
        "phase": "盤前"
      },
      "news": [
        {
          "headline": "These 7 Stocks Will Solve AI’s Most Important Bottleneck",
          "datetime": 1782859817,
          "source": "Yahoo Finance",
          "url": "https://247wallst.com/investing/2026/06/29/these-7-stocks-will-solve-ais-most-important-bottleneck/"
        }
      ]
    },
    "ONDS": {
      "quote": {
        "c": 8.27,
        "d": 0.25,
        "dp": 3.1172,
        "regular": 8.24,
        "reg_d": 0.22,
        "reg_dp": 2.7431,
        "pre": 8.27,
        "post": null,
        "prev_close": 8.02,
        "phase": "盤前"
      },
      "news": [
        {
          "headline": "Ondas Inc. (ONDS) Receives More Than $40 million in New Orders for Autonomous Defense Systems",
          "datetime": 1782859817,
          "source": "Yahoo Finance",
          "url": "https://finance.yahoo.com/markets/stocks/articles/ondas-inc-onds-receives-more-163455163.html"
        }
      ]
    },
    "MRVL": {
      "quote": {
        "c": 292.0,
        "d": 14.25,
        "dp": 5.1305,
        "regular": 297.89,
        "reg_d": 20.14,
        "reg_dp": 7.2511,
        "pre": 292.0,
        "post": null,
        "prev_close": 277.75,
        "phase": "盤前"
      },
      "news": [
        {
          "headline": "Dow Jones Futures: Market Extends Rebound, Bloom Energy Soars Late. SpaceX's First Entry?",
          "datetime": 1782859817,
          "source": "Yahoo Finance",
          "url": "https://www.investors.com/market-trend/stock-market-today/dow-jones-futures-market-rebound-bloom-energy-spacex-buy-point/?src=A00220&yptr=yahoo"
        }
      ]
    },
    "GOOG": {
      "quote": {
        "c": 354.49,
        "d": 3.21,
        "dp": 0.9138,
        "regular": 353.33,
        "reg_d": 2.05,
        "reg_dp": 0.5836,
        "pre": 354.49,
        "post": null,
        "prev_close": 351.28,
        "phase": "盤前"
      },
      "news": [
        {
          "headline": "Tech stocks today: Tech stocks recover as second quarter comes to a close",
          "datetime": 1782859817,
          "source": "Yahoo Finance",
          "url": "https://finance.yahoo.com/technology/live/tech-stocks-today-tech-stocks-recover-as-second-quarter-comes-to-a-close-151053436.html"
        }
      ]
    },
    "SPCX": {
      "quote": {
        "c": 173.85,
        "d": 9.66,
        "dp": 5.8834,
        "regular": 170.86,
        "reg_d": 6.67,
        "reg_dp": 4.0624,
        "pre": 173.85,
        "post": null,
        "prev_close": 164.19,
        "phase": "盤前"
      },
      "news": [
        {
          "headline": "Dow Jones Futures: Market Extends Rebound, Bloom Energy Soars Late. SpaceX's First Entry?",
          "datetime": 1782859817,
          "source": "Yahoo Finance",
          "url": "https://www.investors.com/market-trend/stock-market-today/dow-jones-futures-market-rebound-bloom-energy-spacex-buy-point/?src=A00220&yptr=yahoo"
        }
      ]
    },
    "TSM": {
      "quote": {
        "c": 475.0,
        "d": 19.9,
        "dp": 4.3727,
        "regular": 477.57,
        "reg_d": 22.47,
        "reg_dp": 4.9374,
        "pre": 475.0,
        "post": null,
        "prev_close": 455.1,
        "phase": "盤前"
      },
      "news": [
        {
          "headline": "Mizuho lifts TSMC CoWoS capacity forecasts as server CPU demand surges",
          "datetime": 1782859817,
          "source": "Yahoo Finance",
          "url": "https://finance.yahoo.com/technology/articles/mizuho-lifts-tsmc-cowos-capacity-224423833.html"
        }
      ]
    },
    "MU": {
      "quote": {
        "c": 1117.97,
        "d": -27.31,
        "dp": -2.3844,
        "regular": 1154.29,
        "reg_d": 9.01,
        "reg_dp": 0.7867,
        "pre": 1117.97,
        "post": null,
        "prev_close": 1145.28,
        "phase": "盤前"
      },
      "news": [
        {
          "headline": "Were the Mag 7 more like the Lag 7 in Q2 2026?",
          "datetime": 1782859817,
          "source": "Yahoo Finance",
          "url": "https://finance.yahoo.com/video/were-the-mag-7-more-like-the-lag-7-in-q2-2026-140012890.html"
        }
      ]
    },
    "SNDK": {
      "quote": {
        "c": 2178.0,
        "d": 127.61,
        "dp": 6.2237,
        "regular": 2273.73,
        "reg_d": 223.34,
        "reg_dp": 10.8926,
        "pre": 2178.0,
        "post": null,
        "prev_close": 2050.39,
        "phase": "盤前"
      },
      "news": [
        {
          "headline": "Update: S&P 500, Nasdaq Composite Close Strongest Quarter in Six Years Amid Gains in Technology, Decline in Crude Oil",
          "datetime": 1782859817,
          "source": "Yahoo Finance",
          "url": "https://finance.yahoo.com/markets/stocks/articles/p-500-nasdaq-composite-close-205610906.html"
        }
      ]
    },
    "TSLA": {
      "quote": {
        "c": 419.09,
        "d": 7.25,
        "dp": 1.7604,
        "regular": 420.6,
        "reg_d": 8.76,
        "reg_dp": 2.127,
        "pre": 419.09,
        "post": null,
        "prev_close": 411.84,
        "phase": "盤前"
      },
      "news": [
        {
          "headline": "Tesla Q2 delivery preview: Europe, international sales the driver as US sales in decline",
          "datetime": 1782859817,
          "source": "Yahoo Finance",
          "url": "https://finance.yahoo.com/markets/stocks/article/tesla-q2-delivery-preview-europe-international-sales-the-driver-as-us-sales-in-decline-152919456.html"
        }
      ]
    }
  }
}