{
  "name": "美股盤前情報資料庫",
  "updated_at": "2026-07-14T23:12:29.917434+08:00",
  "next_update_at": "2026-07-14T15:20:00Z",
  "stocks": [
    "MSFT",
    "GOOG",
    "NVDA",
    "NOW",
    "TSM",
    "MRVL",
    "AVGO",
    "MU",
    "SNDK",
    "SPCX"
  ],
  "data": {
    "MSFT": {
      "name": "Microsoft Corporation",
      "quote": {
        "c": 386.12,
        "d": -4.87,
        "dp": -1.2456,
        "regular": 386.12,
        "reg_d": -4.87,
        "reg_dp": -1.2456,
        "pre": null,
        "post": null,
        "prev_close": 390.99,
        "phase": "正式盤"
      },
      "news": [
        {
          "headline": "'Scam Altman strikes again': Why SpaceX CEO Elon Musk was beefing on X over the weekend",
          "datetime": 1783983565,
          "source": "Yahoo Finance",
          "url": "https://finance.yahoo.com/video/scam-altman-strikes-again-why-spacex-ceo-elon-musk-was-beefing-on-x-over-the-weekend-202657668.html"
        }
      ]
    },
    "GOOG": {
      "name": "Alphabet Inc.",
      "quote": {
        "c": 355.75,
        "d": 5.08,
        "dp": 1.4487,
        "regular": 355.75,
        "reg_d": 5.08,
        "reg_dp": 1.4487,
        "pre": null,
        "post": null,
        "prev_close": 350.67,
        "phase": "正式盤"
      },
      "news": [
        {
          "headline": "Meta's data center costs are skyrocketing. Here's what you need to know.",
          "datetime": 1783983565,
          "source": "Yahoo Finance",
          "url": "https://finance.yahoo.com/video/metas-data-center-costs-are-skyrocketing-heres-what-you-need-to-know-203416070.html"
        }
      ]
    },
    "NVDA": {
      "name": "NVIDIA Corporation",
      "quote": {
        "c": 207.97,
        "d": 4.44,
        "dp": 2.1823,
        "regular": 207.97,
        "reg_d": 4.44,
        "reg_dp": 2.1823,
        "pre": null,
        "post": null,
        "prev_close": 203.53,
        "phase": "正式盤"
      },
      "news": [
        {
          "headline": "Why Fortune 500 companies are flocking to open source AI",
          "datetime": 1783983565,
          "source": "Yahoo Finance",
          "url": "https://finance.yahoo.com/video/why-fortune-500-companies-are-flocking-to-open-source-ai-223952992.html"
        }
      ]
    },
    "NOW": {
      "name": "ServiceNow, Inc.",
      "quote": {
        "c": 106.25,
        "d": -5.01,
        "dp": -4.4985,
        "regular": 106.25,
        "reg_d": -5.01,
        "reg_dp": -4.4985,
        "pre": null,
        "post": null,
        "prev_close": 111.26,
        "phase": "正式盤"
      },
      "news": [
        {
          "headline": "3 Profitable Stocks for Long-Term Investors",
          "datetime": 1783983565,
          "source": "Yahoo Finance",
          "url": "https://finance.yahoo.com/markets/stocks/articles/3-profitable-stocks-long-term-160639882.html"
        }
      ]
    },
    "TSM": {
      "name": "Taiwan Semiconductor Manufactur",
      "quote": {
        "c": 425.42,
        "d": 3.84,
        "dp": 0.9109,
        "regular": 425.42,
        "reg_d": 3.84,
        "reg_dp": 0.9109,
        "pre": null,
        "post": null,
        "prev_close": 421.58,
        "phase": "正式盤"
      },
      "news": [
        {
          "headline": "Analyst Dan Ives Calls Memory Chips the “Golden Child” of the AI Revolution with “15-to-1” Demand-to-Supply Imbalance",
          "datetime": 1783983565,
          "source": "Yahoo Finance",
          "url": "https://247wallst.com/investing/2026/07/13/analyst-dan-ives-calls-memory-chips-the-golden-child-of-the-ai-revolution-with-15-to-1-demand-to-supply-imbalance/"
        }
      ]
    },
    "MRVL": {
      "name": "Marvell Technology, Inc.",
      "quote": {
        "c": 225.37,
        "d": 7.84,
        "dp": 3.6041,
        "regular": 225.37,
        "reg_d": 7.84,
        "reg_dp": 3.6041,
        "pre": null,
        "post": null,
        "prev_close": 217.53,
        "phase": "正式盤"
      },
      "news": [
        {
          "headline": "Arm And Marvell Tumble As Chip Stocks Sell Off",
          "datetime": 1783983565,
          "source": "Yahoo Finance",
          "url": "https://www.investors.com/news/technology/chip-stocks-sox-arm-marvell-sell-off/?src=A00220&yptr=yahoo"
        }
      ]
    },
    "AVGO": {
      "name": "Broadcom Inc.",
      "quote": {
        "c": 395.8,
        "d": 11.75,
        "dp": 3.0582,
        "regular": 395.8,
        "reg_d": 11.75,
        "reg_dp": 3.0582,
        "pre": null,
        "post": null,
        "prev_close": 384.05,
        "phase": "正式盤"
      },
      "news": [
        {
          "headline": "Nvidia, Micron, and other chip players are poised to become cash-producing machines",
          "datetime": 1783983565,
          "source": "Yahoo Finance",
          "url": "https://finance.yahoo.com/markets/article/nvidia-micron-and-other-chip-players-are-poised-to-become-cash-producing-machines-150232841.html"
        }
      ]
    },
    "MU": {
      "name": "Micron Technology, Inc.",
      "quote": {
        "c": 975.05,
        "d": 38.05,
        "dp": 4.0608,
        "regular": 975.05,
        "reg_d": 38.05,
        "reg_dp": 4.0608,
        "pre": null,
        "post": null,
        "prev_close": 937.0,
        "phase": "正式盤"
      },
      "news": [
        {
          "headline": "What investors can expect this earnings season",
          "datetime": 1783983565,
          "source": "Yahoo Finance",
          "url": "https://finance.yahoo.com/video/what-investors-can-expect-this-earnings-season-205336498.html"
        }
      ]
    },
    "SNDK": {
      "name": "Sandisk Corporation",
      "quote": {
        "c": 1753.0,
        "d": 79.03,
        "dp": 4.7211,
        "regular": 1753.0,
        "reg_d": 79.03,
        "reg_dp": 4.7211,
        "pre": null,
        "post": null,
        "prev_close": 1673.97,
        "phase": "正式盤"
      },
      "news": [
        {
          "headline": "Retail investors are cashing out of Apple, Tesla, and chip stocks: Chart of the Day",
          "datetime": 1783983565,
          "source": "Yahoo Finance",
          "url": "https://finance.yahoo.com/markets/article/retail-investors-are-cashing-out-of-apple-tesla-and-chip-stocks-chart-of-the-day-162404788.html"
        }
      ]
    },
    "SPCX": {
      "name": "Space Exploration Technologies",
      "quote": {
        "c": 141.92,
        "d": 2.78,
        "dp": 1.998,
        "regular": 141.92,
        "reg_d": 2.78,
        "reg_dp": 1.998,
        "pre": null,
        "post": null,
        "prev_close": 139.14,
        "phase": "正式盤"
      },
      "news": [
        {
          "headline": "As SpaceX stock dips near IPO price, bulls like BofA's Epstein say buy on 'launch leadership'",
          "datetime": 1783983565,
          "source": "Yahoo Finance",
          "url": "https://finance.yahoo.com/markets/stocks/article/as-spacex-stock-dips-near-ipo-price-bulls-like-bofas-epstein-say-buy-on-launch-leadership-150227637.html"
        }
      ]
    }
  },
  "alert_sent": {
    "morning": "2026-07-14",
    "evening": "2026-07-14"
  }
}